dotem.py
hook.sh
dotem-0.1.1.dist-info/LICENSE
dotem-0.1.1.dist-info/METADATA
dotem-0.1.1.dist-info/WHEEL
dotem-0.1.1.dist-info/entry_points.txt
dotem-0.1.1.dist-info/RECORD
