Metadata-Version: 2.1
Name: dotem
Version: 0.1.1
Summary: An environment variable loader for your shell
Home-page: https://github.com/hanhwanglim/dotem
License: MIT
Author: Han Hwang Lim
Author-email: hanhwanglim@gmail.com
Requires-Python: >=3.8,<4.0
Classifier: License :: OSI Approved :: MIT License
Classifier: Programming Language :: Python :: 3
Classifier: Programming Language :: Python :: 3.8
Classifier: Programming Language :: Python :: 3.9
Classifier: Programming Language :: Python :: 3.10
Classifier: Programming Language :: Python :: 3.11
Classifier: Programming Language :: Python :: 3.12
Requires-Dist: tomli (>=2.0.1,<3.0.0)
Requires-Dist: typer[all] (>=0.9.0,<0.10.0)
Project-URL: Repository, https://github.com/hanhwanglim/dotem
